ramlfications/__init__.py
ramlfications/__main__.py
ramlfications/_helpers.py
ramlfications/config.py
ramlfications/errors.py
ramlfications/loader.py
ramlfications/parameters.py
ramlfications/parser.py
ramlfications/raml.py
ramlfications/tree.py
ramlfications/utils.py
ramlfications/validate.py
ramlfications/data/supported_mime_types.json
ramlfications-0.1.3.dist-info/DESCRIPTION.rst
ramlfications-0.1.3.dist-info/entry_points.txt
ramlfications-0.1.3.dist-info/METADATA
ramlfications-0.1.3.dist-info/metadata.json
ramlfications-0.1.3.dist-info/RECORD
ramlfications-0.1.3.dist-info/top_level.txt
ramlfications-0.1.3.dist-info/WHEEL
