Metadata-Version: 2.0
Name: ramlfications
Version: 0.1.3
Summary: A Python RAML parser
Home-page: https://ramlfications.readthedocs.org
Author: Lynn Root
Author-email: lynn@spotify.com
License: Apache 2.0
Keywords: raml,rest
Platform: UNKNOWN
Classifier: Development Status :: 4 – Beta
Classifier: Intended Audience :: Developers
Classifier: Natural Language :: English
Classifier: License :: Apache License 2.0
Classifier: Operating System :: OS Independent
Classifier: Programming Language :: Python
Classifier: Programming Language :: Python :: 2
Classifier: Programming Language :: Python :: 2.6
Classifier: Programming Language :: Python :: 2.7
Classifier: Programming Language :: Python :: 3
Classifier: Programming Language :: Python :: 3.3
Classifier: Programming Language :: Python :: 3.4
Classifier: Programming Language :: Python :: Implementation :: CPython
Classifier: Programming Language :: Python :: Implementation :: PyPy
Classifier: Topic :: Software Development :: Libraries :: Python Modules
Requires-Dist: attrs
Requires-Dist: click
Requires-Dist: markdown2
Requires-Dist: pyyaml
Requires-Dist: six
Requires-Dist: termcolor
Requires-Dist: xmltodict
Provides-Extra: all
Requires-Dist: requests[security]; extra == 'all'
